[
  {
    "inputs": [
      {
        "internalType": "address",
        "name": "token0Address",
        "type": "address"
      },
      {
        "internalType": "address",
        "name": "token1Address",
        "type": "address"
      },
      {
        "internalType": "address",
        "name": "poolOwner",
        "type": "address"
      },
      {
        "internalType": "address",
        "name": "wrapperAddress",
        "type": "address"
      },
      {
        "internalType": "uint256",
        "name": "feePercent",
        "type": "uint256"
      }
    ],
    "stateMutability": "nonpayable",
    "type": "constructor"
  },
  {
    "anonymous": false,
    "inputs": [
      {
        "indexed": true,
        "internalType": "address",
        "name": "to",
        "type": "address"
      },
      {
        "indexed": false,
        "internalType": "uint256",
        "name": "token0",
        "type": "uint256"
      },
      {
        "indexed": false,
        "internalType": "uint256",
        "name": "token1",
        "type": "uint256"
      }
    ],
    "name": "ClaimRewards",
    "type": "event"
  },
  {
    "anonymous": false,
    "inputs": [
      {
        "indexed": true,
        "internalType": "address",
        "name": "from",
        "type": "address"
      },
      {
        "indexed": false,
        "internalType": "uint256",
        "name": "amount0",
        "type": "uint256"
      },
      {
        "indexed": false,
        "internalType": "uint256",
        "name": "amount1",
        "type": "uint256"
      }
    ],
    "name": "Deposit",
    "type": "event"
  },
  {
    "anonymous": false,
    "inputs": [
      {
        "indexed": true,
        "internalType": "address",
        "name": "fromToken",
        "type": "address"
      },
      {
        "indexed": true,
        "internalType": "address",
        "name": "toToken",
        "type": "address"
      },
      {
        "indexed": false,
        "internalType": "uint256",
        "name": "amountSpend",
        "type": "uint256"
      },
      {
        "indexed": false,
        "internalType": "uint256",
        "name": "amountReceived",
        "type": "uint256"
      }
    ],
    "name": "Exchange",
    "type": "event"
  },
  {
    "anonymous": false,
    "inputs": [
      {
        "indexed": true,
        "internalType": "address",
        "name": "from",
        "type": "address"
      },
      {
        "indexed": true,
        "internalType": "address",
        "name": "to",
        "type": "address"
      }
    ],
    "name": "TransferOwnership",
    "type": "event"
  },
  {
    "anonymous": false,
    "inputs": [
      {
        "indexed": true,
        "internalType": "address",
        "name": "to",
        "type": "address"
      },
      {
        "indexed": false,
        "internalType": "uint256",
        "name": "amount0",
        "type": "uint256"
      },
      {
        "indexed": false,
        "internalType": "uint256",
        "name": "amount1",
        "type": "uint256"
      }
    ],
    "name": "Withdraw",
    "type": "event"
  },
  {
    "inputs": [],
    "name": "claimRewards",
    "outputs": [],
    "stateMutability": "nonpayable",
    "type": "function"
  },
  {
    "inputs": [
      {
        "internalType": "uint256",
        "name": "amount0",
        "type": "uint256"
      },
      {
        "internalType": "uint256",
        "name": "amount1",
        "type": "uint256"
      }
    ],
    "name": "depositTokens",
    "outputs": [],
    "stateMutability": "payable",
    "type": "function"
  },
  {
    "inputs": [
      {
        "internalType": "address",
        "name": "tokenAddress",
        "type": "address"
      },
      {
        "internalType": "uint256",
        "name": "amount",
        "type": "uint256"
      }
    ],
    "name": "estimateExchangeAmount",
    "outputs": [
      {
        "internalType": "uint256",
        "name": "",
        "type": "uint256"
      }
    ],
    "stateMutability": "view",
    "type": "function"
  },
  {
    "inputs": [
      {
        "internalType": "address",
        "name": "account",
        "type": "address"
      }
    ],
    "name": "estimateRewardsAmount",
    "outputs": [
      {
        "internalType": "uint256[2]",
        "name": "",
        "type": "uint256[2]"
      }
    ],
    "stateMutability": "view",
    "type": "function"
  },
  {
    "inputs": [
      {
        "internalType": "uint8",
        "name": "withdrawPercent",
        "type": "uint8"
      }
    ],
    "name": "estimateWithdrawAmount",
    "outputs": [
      {
        "internalType": "uint256[2]",
        "name": "",
        "type": "uint256[2]"
      }
    ],
    "stateMutability": "view",
    "type": "function"
  },
  {
    "inputs": [
      {
        "internalType": "address",
        "name": "tokenAddress",
        "type": "address"
      },
      {
        "internalType": "uint256",
        "name": "amount",
        "type": "uint256"
      }
    ],
    "name": "exchangeToken",
    "outputs": [],
    "stateMutability": "nonpayable",
    "type": "function"
  },
  {
    "inputs": [],
    "name": "fee",
    "outputs": [
      {
        "internalType": "uint256",
        "name": "",
        "type": "uint256"
      }
    ],
    "stateMutability": "view",
    "type": "function"
  },
  {
    "inputs": [],
    "name": "feeDenominator",
    "outputs": [
      {
        "internalType": "uint256",
        "name": "",
        "type": "uint256"
      }
    ],
    "stateMutability": "view",
    "type": "function"
  },
  {
    "inputs": [],
    "name": "getAccountData",
    "outputs": [
      {
        "components": [
          {
            "internalType": "uint256[2]",
            "name": "shares",
            "type": "uint256[2]"
          },
          {
            "internalType": "uint256[2]",
            "name": "deposits",
            "type": "uint256[2]"
          },
          {
            "internalType": "uint256[2]",
            "name": "rewards",
            "type": "uint256[2]"
          }
        ],
        "internalType": "struct IKPool.AccountData",
        "name": "",
        "type": "tuple"
      }
    ],
    "stateMutability": "view",
    "type": "function"
  },
  {
    "inputs": [
      {
        "internalType": "address",
        "name": "_token0Address",
        "type": "address"
      }
    ],
    "name": "isLTR",
    "outputs": [
      {
        "internalType": "bool",
        "name": "",
        "type": "bool"
      }
    ],
    "stateMutability": "view",
    "type": "function"
  },
  {
    "inputs": [],
    "name": "owner",
    "outputs": [
      {
        "internalType": "address",
        "name": "",
        "type": "address"
      }
    ],
    "stateMutability": "view",
    "type": "function"
  },
  {
    "inputs": [],
    "name": "sharesDenominator",
    "outputs": [
      {
        "internalType": "uint256",
        "name": "",
        "type": "uint256"
      }
    ],
    "stateMutability": "view",
    "type": "function"
  },
  {
    "inputs": [],
    "name": "token0",
    "outputs": [
      {
        "internalType": "address",
        "name": "",
        "type": "address"
      }
    ],
    "stateMutability": "view",
    "type": "function"
  },
  {
    "inputs": [],
    "name": "token1",
    "outputs": [
      {
        "internalType": "address",
        "name": "",
        "type": "address"
      }
    ],
    "stateMutability": "view",
    "type": "function"
  },
  {
    "inputs": [
      {
        "internalType": "address",
        "name": "to",
        "type": "address"
      }
    ],
    "name": "transferOwnership",
    "outputs": [],
    "stateMutability": "nonpayable",
    "type": "function"
  },
  {
    "inputs": [
      {
        "internalType": "uint8",
        "name": "withdrawPercent",
        "type": "uint8"
      }
    ],
    "name": "withdrawTokens",
    "outputs": [],
    "stateMutability": "nonpayable",
    "type": "function"
  }
]
